{
    "id": 266,
    "egg_groups": [
        "bug"
    ],
    "hatch_counter": 15,
    "abilities": [
        {
            "slot": 1,
            "is_hidden": false,
            "ability": {
                "url": "https://pokeapi.co/api/v2/ability/61/",
                "name": "shed-skin",
                "id": 61
            }
        }
    ],
    "stats": [
        {
            "id": 1,
            "base_stat": 50
        },
        {
            "id": 2,
            "base_stat": 35
        },
        {
            "id": 3,
            "base_stat": 55
        },
        {
            "id": 4,
            "base_stat": 25
        },
        {
            "id": 5,
            "base_stat": 25
        },
        {
            "id": 6,
            "base_stat": 15
        }
    ],
    "habitat": "forest",
    "weight": 100,
    "generation": "generation-iii",
    "base_happiness": 70,
    "height": 6,
    "evolution_chain": 135,
    "capture_rate": 120,
    "base_experience": 72,
    "names": [
        {
            "name": "Karasalis",
            "language": "roomaji"
        },
        {
            "name": "실쿤",
            "language": "ko"
        },
        {
            "name": "Armulys",
            "language": "fr"
        },
        {
            "name": "Schaloko",
            "language": "de"
        },
        {
            "name": "Silcoon",
            "language": "es"
        },
        {
            "name": "Silcoon",
            "language": "it"
        },
        {
            "name": "Silcoon",
            "language": "en"
        },
        {
            "name": "カラサリス",
            "language": "ja"
        }
    ],
    "growth_rate": {
        "url": "https://pokeapi.co/api/v2/growth-rate/2/",
        "name": "medium"
    },
    "gender_rate": 4,
    "moves": [
        {
            "move_learn_method": "level-up",
            "level_learned_at": 6,
            "name": "tackle",
            "id": "33"
        },
        {
            "move_learn_method": "level-up",
            "level_learned_at": 1,
            "name": "poison-sting",
            "id": "40"
        },
        {
            "move_learn_method": "tutor",
            "level_learned_at": 0,
            "name": "string-shot",
            "id": "81"
        },
        {
            "move_learn_method": "level-up",
            "level_learned_at": 1,
            "name": "harden",
            "id": "106"
        },
        {
            "move_learn_method": "tutor",
            "level_learned_at": 0,
            "name": "iron-defense",
            "id": "334"
        },
        {
            "move_learn_method": "tutor",
            "level_learned_at": 0,
            "name": "bug-bite",
            "id": "450"
        },
        {
            "move_learn_method": "tutor",
            "level_learned_at": 0,
            "name": "electroweb",
            "id": "527"
        }
    ],
    "flavor_text": "SILCOON tethers itself to a tree branch using silk to keep from falling. There,  this POKéMON hangs quietly while it awaits evolution. It peers out of the silk cocoon through a small hole.",
    "types": [
        {
            "slot": 1,
            "id": 7
        }
    ],
    "image": "https://www.pokemon.com/static-assets/content-assets/cms2/img/pokedex/detail/266.png"
}